{
	"Configuration Version": "1.0.0",
	"SUPPORTED_PLUGIN_VERSIONS": "[3.1.0]",
	"CHANGELOG_DESCRIPTION": "Zeigt den neusten Changelog an.",
	"COMMAND_NOT_FOUND": "Befehl nicht gefunden!",
	"COMMAND_SYNTAX_MESSAGE": "Syntax: /ct {SYNTAX}",
	"DROP_DESCRIPTION": "Sorgt dafür, dass der ausgewählte Spieler sein Item fallen lässt!",
	"DROP_PLAYER_ITEM_DROP": "{PLAYER_NAME} lässt sein Item fallen!",
	"DROP_PLAYER_NOT_HOLD_ANY_ITEM": "{PLAYER_NAME} hat kein Item in der Hand!",
	"EXPLODE_DESCRIPTION": "Lässt den ausgewählten Spieler explodieren!",
	"EXPLODE_PLAYER_EXPLODED": "{PLAYER_NAME} ist explodiert!",
	"FAKE_OP_DESCRIPTION": "Der ausgewählte Spieler denkt, dass er OP hat!",
	"FAKE_OP_EXECUTE": "{PLAYER_NAME} denkt nun, dass er OP hat!",
	"FREEZE_DESCRIPTION": "Friert den ausgewählten Spieler ein!",
	"FREEZE_TARGET_FROZEN": "{PLAYER_NAME} ist nun eingefroren!",
	"FREEZE_TARGET_NOT_FROZEN_ANYMORE": "{PLAYER_NAME} ist nun nicht mehr eingefroren!",
	"GODMODE_DESCRIPTION": "Aktiviert den Godmode!",
	"GODMODE_ENABLED": "Godmode aktiviert!",
	"GODMODE_DISABLED": "Godmode deaktiviert!",
	"HELP_MESSAGE": "Gib /ct help ein für Hilfe!",
	"INVALID_COMMAND_ARGUMENTS": "Ungültige Befehl Argumente!",
	"INVENTORY_DROP_DESCRIPTION": "Sorgt dafür, dass der ausgewählte Spieler sein ganzes Inventar entleert.",
	"INVENTORY_DROP_TARGET_DROP": "{PLAYER_NAME} hat sein Inventar entleert!",
	"INVENTORY_FULL": "Dein Inventar ist voll!",
	"LANGUAGE_DESCRIPTION": "Du kannst hier zwischen verschiedenen Sprachen wechseln!",
	"LANGUAGE_FILE_CREDITS": "Diese Sprachdatei wurde von CrashedLife erstellt!",
	"LANGUAGE_FILE_OUTDATED": "Deine Sprachdatei ist veraltet! Bitte warte auf eine Aktualisierung!",
	"LANGUAGE_FILE_SEARCH_UPDATE": "Wir versuchen eine neue Version für deine Sprachdateien zu finden...",
	"LANGUAGE_FILE_SEARCH_UPDATE_DONE": "Aktualisierungssuche abgeschlossen!",
	"LANGUAGE_LISTING": "Sprachen:",
	"LANGUAGE_NOT_FOUND": "Sprache nicht gefunden!",
	"LANGUAGE_SWITCHED": "Du hast erfolgreich die Sprache zu Deutsch geändert!"
	"MODES": "Modi:",
	"MODE_NOT_FOUND": "Fehler: Modus nicht gefunden!",
	"NO_BLOCK_BREAK_DESCRIPTION": "Verhindert, dass der ausgewählte Spieler Blöcke abbauen kann!",
	"NO_BLOCK_BREAK_PLAYER_DISABLE_BLOCK_BREAK": "{PLAYER_NAME} kann keine Blöcke mehr abbauen!",
	"NO_BLOCK_BREAK_PLAYER_ENABLE_BLOCK_BREAK": "{PLAYER_NAME} kann wieder Blöcke abbauen!",
	"NO_BLOCK_PLACE_DESCRIPTION": "Verhindert, dass der ausgewählte Spieler Blöcke platzieren kann!",
	"NO_BLOCK_PLACE_PLAYER_DISABLE_BLOCK_PLACE": "{PLAYER_NAME} kann keine Blöcke mehr platzieren!",
	"NO_BLOCK_PLACE_PLAYER_ENABLE_BLOCK_PLACE": "{PLAYER_NAME} kann wieder Blöcke platzieren!",
	"NO_PERMISSIONS": "Du hast keine Berechtigungen um diesen Befehl auszuführen!",
	"PLAYER_OFFLINE": "Dieser Spieler ist offline!",
	"ROCKET_DESCRIPTION": "Schleudert den ausgewählten Spieler in die Luft!",
	"ROCKET_PLAYER_LAUNCH": "{PLAYER_NAME} wurde in die Luft geschleudert!",
	"SCREEN_BLOCK_DESCRIPTION": "Blockiert die Aktionen in Behältern oder Inventaren auf seinem Bildschirm!",
	"SCREEN_BLOCK_DISABLED": "{PLAYER_NAME} kann wieder Behälter verwenden!",
	"SCREEN_BLOCK_ENABLED": "{PLAYER_NAME} kann keine Behälter mehr verwenden!",
	"SCREEN_CREDITS_DESCRIPTION": "Zeigt den Mitwirkenden Bildschirm an!",
	"SCREEN_CREDITS_SHOW": "{PLAYER_NAME} sieht nun den Mitwirkenden Bildschirm!",
	"SCREEN_DEMO_DESCRIPTION": "Zeigt den Demo Bildschirm an!",
	"SCREEN_DEMO_SHOW": "{PLAYER_NAME} sieht nun den Demo Bildschirm!",
	"SCREEN_DESCRIPTION": "Macht komische Dinge auf dem Bildschirm vom ausgewählten Spieler!",
	"SCREEN_GUARDIAN_DESCRIPTION": "Zeigt den Wächter auf dem Bildschirm an!",
	"SCREEN_GUARDIAN_SHOW": "{PLAYER_NAME} sieht nun ein Wächter auf dem Bildschirm!",
	"TEAM_CHAT_BROADCAST_LOGIN": "{PLAYER_NAME} hat sich im Chat eingeloggt!",
	"TEAM_CHAT_BROADCAST_LOGOUT": "{PLAYER_NAME} hat sich im Chat ausgeloggt",
	"TEAM_CHAT_DESCRIPTION": "Erlaubt den Trollern einen privaten Chat zu führen!",
	"TEAM_CHAT_PLAYER_LOGIN": "Du hast dich im Chat eingeloggt!",
	"TEAM_CHAT_PLAYER_LOGOUT": "Du hast dich im Chat ausgeloggt!",
	"TROLL_ITEM_ALREADY_OWNED": "Du hast bereits dieses Item!"
	"TROLL_ITEM_DESCRIPTION": "Öffnet das CrashedTroll GUI!",
	"TROLL_ITEM_OTHER_PLAYER_ITEM_DESCRIPTION": "Funktionen zum trollen von anderen Spielern!",
	"TROLL_ITEM_PLAYER_ITEM_DESCRIPTION": "Funktionen für den eigenen Spieler!",
	"UPDATE_FOUND": "Aktualisierung gefunden! Bitte aktualisiere das Plugin auf die neuste Version, für neue coole Funktionen und Verbesserungen!"
}